green_whatsapp_server/__init__.py
green_whatsapp_server/server.py
green_whatsapp_mcp_server-0.1.16.dist-info/METADATA
green_whatsapp_mcp_server-0.1.16.dist-info/WHEEL
green_whatsapp_mcp_server-0.1.16.dist-info/entry_points.txt
green_whatsapp_mcp_server-0.1.16.dist-info/licenses/LICENSE
green_whatsapp_mcp_server-0.1.16.dist-info/RECORD
